pypitchfx/__init__.py
pypitchfx/scrape.py
pypitchfx/gameday_model/Action.py
pypitchfx/gameday_model/AtBat.py
pypitchfx/gameday_model/Game.py
pypitchfx/gameday_model/GamePlayer.py
pypitchfx/gameday_model/HalfInning.py
pypitchfx/gameday_model/Inning.py
pypitchfx/gameday_model/Pickoff.py
pypitchfx/gameday_model/Pitch.py
pypitchfx/gameday_model/Runner.py
pypitchfx/load/create_tables.py
pypitchfx/load/load_games.py
pypitchfx/load/load_players.py
pypitchfx/load/queries.py
pypitchfx-1.0.4.dist-info/LICENSE
pypitchfx-1.0.4.dist-info/METADATA
pypitchfx-1.0.4.dist-info/WHEEL
pypitchfx-1.0.4.dist-info/top_level.txt
pypitchfx-1.0.4.dist-info/RECORD
