Metadata-Version: 2.1
Name: pypitchfx
Version: 1.0.4
Summary: Tool for parsing mlb gameday data
Home-page: http://github.com/JavierPalomares90/pypitchfx
Author: Javier Palomares
Author-email: javier.palomares.90@gmail.com
License: MIT
Platform: UNKNOWN
Requires-Dist: beautifulsoup4
Requires-Dist: lxml
Requires-Dist: sqlalchemy
